streamlit_image_coordinates/__init__.py
streamlit_image_coordinates/frontend/index.html
streamlit_image_coordinates/frontend/main.js
streamlit_image_coordinates/frontend/streamlit-component-lib.js
streamlit_image_coordinates/frontend/style.css
streamlit_image_coordinates-0.1.9.dist-info/LICENSE
streamlit_image_coordinates-0.1.9.dist-info/METADATA
streamlit_image_coordinates-0.1.9.dist-info/WHEEL
streamlit_image_coordinates-0.1.9.dist-info/top_level.txt
streamlit_image_coordinates-0.1.9.dist-info/RECORD
