Metadata-Version: 2.1
Name: streamlit-image-coordinates
Version: 0.1.9
Summary: Streamlit component that displays an image and returns the coordinates when you click on it
Home-page: https://github.com/blackary/streamlit-image-coordinates/
Author: Zachary Blackwood
Author-email: zachary@streamlit.io
License: MIT License
Keywords: python streamlit images component
Classifier: Development Status :: 3 - Alpha
Classifier: Intended Audience :: Developers
Classifier: Topic :: Software Development :: Libraries :: Python Modules
Classifier: License :: OSI Approved :: MIT License
Classifier: Programming Language :: Python :: 3
Classifier: Programming Language :: Python :: 3.7
Classifier: Programming Language :: Python :: 3.8
Classifier: Programming Language :: Python :: 3.9
Classifier: Programming Language :: Python :: 3.10
Requires-Python: >=3.7
License-File: LICENSE
Requires-Dist: streamlit>=1.2
Requires-Dist: jinja2
